karrio/mappers/asendia_us/__init__.py
karrio/mappers/asendia_us/mapper.py
karrio/mappers/asendia_us/proxy.py
karrio/mappers/asendia_us/settings.py
karrio/plugins/asendia_us/__init__.py
karrio/providers/asendia_us/__init__.py
karrio/providers/asendia_us/error.py
karrio/providers/asendia_us/rate.py
karrio/providers/asendia_us/tracking.py
karrio/providers/asendia_us/units.py
karrio/providers/asendia_us/utils.py
karrio/providers/asendia_us/shipment/__init__.py
karrio/providers/asendia_us/shipment/cancel.py
karrio/providers/asendia_us/shipment/create.py
karrio/schemas/asendia_us/__init__.py
karrio/schemas/asendia_us/cancel_request.py
karrio/schemas/asendia_us/cancel_response.py
karrio/schemas/asendia_us/error_response.py
karrio/schemas/asendia_us/rate_request.py
karrio/schemas/asendia_us/rate_response.py
karrio/schemas/asendia_us/shipping_request.py
karrio/schemas/asendia_us/shipping_response.py
karrio/schemas/asendia_us/tracking_request.py
karrio/schemas/asendia_us/tracking_response.py
karrio_asendia_us-2026.1.4.dist-info/METADATA
karrio_asendia_us-2026.1.4.dist-info/WHEEL
karrio_asendia_us-2026.1.4.dist-info/entry_points.txt
karrio_asendia_us-2026.1.4.dist-info/top_level.txt
karrio_asendia_us-2026.1.4.dist-info/RECORD
